{
  "number": 84,
  "name": "Al-Inshiqaq",
  "arabic_name": "الإنشقاق",
  "translation": "Terbelah",
  "revelation_type": "meccan",
  "ayah_count": 25,
  "ayahs": [
    {
      "number": 1,
      "arabic": "إِذَا ٱلسَّمَآءُ ٱنشَقَّتۡ",
      "translation": "Apabila langit terbelah"
    },
    {
      "number": 2,
      "arabic": "وَأَذِنَتۡ لِرَبِّهَا وَحُقَّتۡ",
      "translation": "dan patuh kepada Tuhannya, dan sudah semestinya patuh"
    },
    {
      "number": 3,
      "arabic": "وَإِذَا ٱلۡأَرۡضُ مُدَّتۡ",
      "translation": "dan apabila bumi diratakan"
    },
    {
      "number": 4,
      "arabic": "وَأَلۡقَتۡ مَا فِيهَا وَتَخَلَّتۡ",
      "translation": "dan memuntahkan apa yang ada di dalamnya dan menjadi kosong"
    },
    {
      "number": 5,
      "arabic": "وَأَذِنَتۡ لِرَبِّهَا وَحُقَّتۡ",
      "translation": "dan patuh kepada Tuhannya, dan sudah semestinya patuh"
    },
    {
      "number": 6,
      "arabic": "يَـٰٓأَيُّهَا ٱلۡإِنسَٰنُ إِنَّكَ كَادِحٌ إِلَىٰ رَبِّكَ كَدۡحٗا فَمُلَٰقِيهِ",
      "translation": "Wahai manusia! Sesungguhnya kamu telah bekerja keras menuju Tuhanmu, maka kamu akan menemui-Nya"
    },
    {
      "number": 7,
      "arabic": "فَأَمَّا مَنۡ أُوتِيَ كِتَٰبَهُۥ بِيَمِينِهِۦ",
      "translation": "Maka adapun orang yang catatanya diberikan dari sebelah kanannya"
    },
    {
      "number": 8,
      "arabic": "فَسَوۡفَ يُحَاسَبُ حِسَابٗا يَسِيرٗا",
      "translation": "maka dia akan diperiksa dengan pemeriksaan yang mudah"
    },
    {
      "number": 9,
      "arabic": "وَيَنقَلِبُ إِلَىٰٓ أَهۡلِهِۦ مَسۡرُورٗا",
      "translation": "dan dia akan kembali kepada keluarganya (yang sama-sama beriman) dengan gembira"
    },
    {
      "number": 10,
      "arabic": "وَأَمَّا مَنۡ أُوتِيَ كِتَٰبَهُۥ وَرَآءَ ظَهۡرِهِۦ",
      "translation": "Dan adapun orang yang catatannya diberikan dari arah belakang"
    },
    {
      "number": 11,
      "arabic": "فَسَوۡفَ يَدۡعُواْ ثُبُورٗا",
      "translation": "maka dia akan berteriak, \"Celakalah aku"
    },
    {
      "number": 12,
      "arabic": "وَيَصۡلَىٰ سَعِيرًا",
      "translation": "Dan dia akan masuk ke dalam api yang menyala-nyala (neraka)"
    },
    {
      "number": 13,
      "arabic": "إِنَّهُۥ كَانَ فِيٓ أَهۡلِهِۦ مَسۡرُورًا",
      "translation": "Sungguh, dia dahulu (di dunia) bergembira di kalangan keluarganya (yang sama-sama kafir)"
    },
    {
      "number": 14,
      "arabic": "إِنَّهُۥ ظَنَّ أَن لَّن يَحُورَ",
      "translation": "Sesungguhnya dia mengira bahwa dia tidak akan kembali (kepada Tuhannya)"
    },
    {
      "number": 15,
      "arabic": "بَلَىٰٓۚ إِنَّ رَبَّهُۥ كَانَ بِهِۦ بَصِيرٗا",
      "translation": "Tidak demikian, sesungguhnya Tuhannya selalu melihatnya"
    },
    {
      "number": 16,
      "arabic": "فَلَآ أُقۡسِمُ بِٱلشَّفَقِ",
      "translation": "Maka Aku bersumpah demi cahaya merah pada waktu senja"
    },
    {
      "number": 17,
      "arabic": "وَٱلَّيۡلِ وَمَا وَسَقَ",
      "translation": "demi malam dan apa yang diselubunginya"
    },
    {
      "number": 18,
      "arabic": "وَٱلۡقَمَرِ إِذَا ٱتَّسَقَ",
      "translation": "demi bulan apabila jadi purnama"
    },
    {
      "number": 19,
      "arabic": "لَتَرۡكَبُنَّ طَبَقًا عَن طَبَقٖ",
      "translation": "sungguh, akan kamu jalani tingkat demi tingkat (dalam kehidupan)"
    },
    {
      "number": 20,
      "arabic": "فَمَا لَهُمۡ لَا يُؤۡمِنُونَ",
      "translation": "Maka mengapa mereka tidak mau beriman"
    },
    {
      "number": 21,
      "arabic": "وَإِذَا قُرِئَ عَلَيۡهِمُ ٱلۡقُرۡءَانُ لَا يَسۡجُدُونَۤ۩",
      "translation": "Dan apabila Alquran dibacakan kepada mereka, mereka tidak (mau) bersujud"
    },
    {
      "number": 22,
      "arabic": "بَلِ ٱلَّذِينَ كَفَرُواْ يُكَذِّبُونَ",
      "translation": "bahkan orang-orang kafir itu mendustakan-(nya)"
    },
    {
      "number": 23,
      "arabic": "وَٱللَّهُ أَعۡلَمُ بِمَا يُوعُونَ",
      "translation": "Dan Allah lebih mengetahui apa yang mereka sembunyikan (dalam hati mereka)"
    },
    {
      "number": 24,
      "arabic": "فَبَشِّرۡهُم بِعَذَابٍ أَلِيمٍ",
      "translation": "Maka sampaikanlah kepada mereka (ancaman) azab yang pedih"
    },
    {
      "number": 25,
      "arabic": "إِلَّا ٱلَّذِينَ ءَامَنُواْ وَعَمِلُواْ ٱلصَّـٰلِحَٰتِ لَهُمۡ أَجۡرٌ غَيۡرُ مَمۡنُونِۭ",
      "translation": "kecuali orang-orang yang beriman dan mengerjakan kebajikan, mereka akan mendapat pahala yang tidak putus-putusnya"
    }
  ]
}